appscommon/__init__.py
appscommon/logconfig.py
appscommon/readonly.py
appscommon/schemas.py
appscommon/db/adapters/__init__.py
appscommon/db/adapters/unit_of_work.py
appscommon/db/interfaces/__init__.py
appscommon/db/interfaces/repository.py
appscommon/db/interfaces/unit_of_work.py
appscommon/domain/__init__.py
appscommon/domain/models/__init__.py
appscommon/domain/models/basemodel.py
appscommon/enums/__init__.py
appscommon/enums/response_status_enum.py
appscommon/exception/__init__.py
appscommon/exception/exceptions.py
appscommon/exception/handler.py
appscommon/exception/message.py
appscommon/flaskutils/__init__.py
appscommon/flaskutils/confighelper.py
appscommon/flaskutils/http/__init__.py
appscommon/flaskutils/http/utils.py
appscommon/flaskutils/http/middleware/__init__.py
appscommon/flaskutils/http/middleware/filters.py
appscommon-0.0.2.dist-info/METADATA
appscommon-0.0.2.dist-info/WHEEL
appscommon-0.0.2.dist-info/top_level.txt
appscommon-0.0.2.dist-info/RECORD
