Metadata-Version: 2.1
Name: appscommon
Version: 0.0.2
Summary: Common utility package.
Author-email: Danush Kumar Baskarraj <danushkumar.baskar@gmail.com>
Project-URL: Homepage, https://github.com/danushk97/componenet-appscommon
Project-URL: Bug Tracker, https://github.com/danushk97/componenet-appscommon/issues
Classifier: Programming Language :: Python :: 3
Classifier: Operating System :: OS Independent
Requires-Python: >=3.9
Requires-Dist: Flask (==2.0.1)
Requires-Dist: pydantic (==1.10.3)
